MANIFEST.in
README.rst
setup.cfg
setup.py
tw2/__init__.py
tw2.huBarcode.egg-info/PKG-INFO
tw2.huBarcode.egg-info/SOURCES.txt
tw2.huBarcode.egg-info/dependency_links.txt
tw2.huBarcode.egg-info/entry_points.txt
tw2.huBarcode.egg-info/namespace_packages.txt
tw2.huBarcode.egg-info/not-zip-safe
tw2.huBarcode.egg-info/requires.txt
tw2.huBarcode.egg-info/top_level.txt
tw2/huBarcode/__init__.py
tw2/huBarcode/samples.py
tw2/huBarcode/widgets.py
tw2/huBarcode/images/__init__.py
tw2/huBarcode/templates/__init__.py
tw2/huBarcode/templates/__init__.pyc
tw2/huBarcode/templates/barcode.html