Metadata-Version: 1.0
Name: tw2.huBarcode
Version: 2.0a5
Summary: toscawidgets2 wrapper for huBarcode
Home-page: UNKNOWN
Author: RemyD
Author-email: remyd@civx.us
License: AGPLv3+
Keywords: toscawidgets.widgets
Platform: UNKNOWN
Classifier: Development Status :: 3 - Alpha
Classifier: Environment :: Web Environment
Classifier: Environment :: Web Environment :: ToscaWidgets
Classifier: Topic :: Software Development :: Libraries :: Python Modules
Classifier: Topic :: Software Development :: Widget Sets
Classifier: Intended Audience :: Developers
Classifier: Operating System :: OS Independent
Classifier: Programming Language :: Python
